code/__init__.py
code/sr.py
iraqCal-1.0.dist-info/LICENSE.txt
iraqCal-1.0.dist-info/METADATA
iraqCal-1.0.dist-info/WHEEL
iraqCal-1.0.dist-info/top_level.txt
iraqCal-1.0.dist-info/RECORD
